LICENSE
MANIFEST.in
README.md
setup.cfg
setup.py
django_todo_api.egg-info/PKG-INFO
django_todo_api.egg-info/SOURCES.txt
django_todo_api.egg-info/dependency_links.txt
django_todo_api.egg-info/not-zip-safe
django_todo_api.egg-info/requires.txt
django_todo_api.egg-info/top_level.txt
todo_api/__init__.py
todo_api/models.py
todo_api/serializers.py
todo_api/testing_utils.py
todo_api/urls.py
todo_api/views.py
todo_api/migrations/0001_initial.py
todo_api/migrations/__init__.py
todo_api/tests/__init__.py
todo_api/tests/test_models.py
todo_api/tests/test_serializers.py
todo_api/tests/test_views.py